{
  "selection": [
    {
      "セットアップ": [
        "選択してください",
        "Vネックニット",
        "ZIPパーカー"
      ]
    }
  ],
  "catchCopy": "【上下セット】ROOM WEAR Vネックニット／ZIPパーカー　セットアップ",
  "itemName": "【上下セット】ROOM WEAR Vネックニット／ZIPパーカー　セットアップ",
  "itemNumber": "TKM211019",
  "price": 14000,
  "priceNoTax": 12728,
  "size": [
    "F"
  ],
  "color": [
    "オフ",
    "チャコール"
  ],
  "description": "おうちでのリラックスタイムにぴったりなもこもこルームウエア\n同素材のパンツとセットアップで着られるモコモコ素材のルームウエア。\nゆったりとしたサイズ感と、ポケット口やフード周りのリブ編みをポイントにした\nシンプルなジップパーカーなので大人女子も着やすい１枚です。\n室内での着用からちょっとお出かけするときのワンマイルウエアとしても重宝します。\n\n\nスペック\nサイズ：F\n着丈：68\n身幅：53\n裄丈：77.5\n\nモデル（身長）：166cm\n\n素材\nポリエステル：100％\n\n※サイズは平置きでの実寸サイズを測っているため、誤差がでる場合がある旨ご了承下さい。",
  "colorCode": {
    "ブラック": "BK",
    "オフホワイト": "WH",
    "ゴールド": "GO",
    "ローズゴールド": "PK",
    "モカ": "MC",
    "シルバー": "SV",
    "サックスブルー": "SX",
    "ネイビー": "NV",
    "ベージュ": "BG",
    "シェリーベージュ": "CB",
    "スキニーベージュ": "SB",
    "サンドベージュ": "SB",
    "チャコール": "CC",
    "チャコールグレー": "CC",
    "オフ×ブラック": "WB",
    "オフ×ネイビー": "WN",
    "テラコッタ": "TC",
    "ライトグリーン": "LG",
    "ミックス": "MX",
    "ネイビーミックス": "MX",
    "ホワイト": "WH",
    "ブラウン": "BR",
    "キャメル": "CA",
    "ドロップ": "DR",
    "グレー": "GL",
    "ピンク": "PK",
    "シャンパン": "CP",
    "リング": "RN",
    "ストレート": "ST",
    "ブルー": "BL",
    "ブルーグレー": "BL",
    "ミント": "MN",
    "トープ": "TP",
    "レッド": "RD",
    "ローズ": "RS",
    "パープル": "PP",
    "カーキ": "KH",
    "サンド": "SD"
  }
}